json2objects/__init__.py
json2objects-0.0.0.1.dist-info/LICENSE
json2objects-0.0.0.1.dist-info/METADATA
json2objects-0.0.0.1.dist-info/WHEEL
json2objects-0.0.0.1.dist-info/top_level.txt
json2objects-0.0.0.1.dist-info/RECORD
